deepverse/__init__.py
deepverse/datasets/__init__.py
deepverse/datasets/dataset.py
deepverse/datasets/sensor_datasets.py
deepverse/datasets/wireless_datasets.py
deepverse/parameter/__init__.py
deepverse/parameter/json_utils.py
deepverse/parameter/matlab_utils.py
deepverse/parameter/parameter_manager.py
deepverse/parameter/yaml_utils.py
deepverse/scenario/__init__.py
deepverse/scenario/moving_object.py
deepverse/scenario/scenario_manager.py
deepverse/scenario/sensor.py
deepverse/visualizers/__init__.py
deepverse/visualizers/base_visualizer.py
deepverse/visualizers/image_visualizer.py
deepverse/visualizers/lidar_visualizer.py
deepverse/visualizers/scene_visualizer.py
deepverse/wireless/Antenna.py
deepverse/wireless/Channel.py
deepverse/wireless/Paths.py
deepverse/wireless/RayTracingLoader.py
deepverse/wireless/Waveform.py
deepverse/wireless/__init__.py
deepverse/wireless/consts.py
deepverse/wireless/process_params.py
deepverse/wireless/utils.py
deepverse-0.0.4.dist-info/METADATA
deepverse-0.0.4.dist-info/WHEEL
deepverse-0.0.4.dist-info/top_level.txt
deepverse-0.0.4.dist-info/RECORD
